{"created_at":"Mon Jul 29 10:48:36 +0000 2019","id":1155792230772367360,"id_str":"1155792230772367360","text":"Thanks #binance!! I just received 2.806619 #BTC! Anyone can join! https:\/\/t.co\/aQUiSy9BlU","truncated":false,"entities":{"hashtags":[{"text":"binance","indices":[7,15]},{"text":"BTC","indices":[43,47]}],"symbols":[],"user_mentions":[],"urls":[],"media":[{"id":1155792195565293569,"id_str":"1155792195565293569","indices":[66,89],"media_url":"http:\/\/pbs.twimg.com\/media\/EAoy4NLWkAEUiQO.png","media_url_https":"https:\/\/pbs.twimg.com\/media\/EAoy4NLWkAEUiQO.png","url":"https:\/\/t.co\/aQUiSy9BlU","display_url":"pic.twitter.com\/aQUiSy9BlU","expanded_url":"https:\/\/twitter.com\/Katheri85041383\/status\/1155792230772367360\/photo\/1","type":"photo","sizes":{"small":{"w":478,"h":547,"resize":"fit"},"medium":{"w":478,"h":547,"resize":"fit"},"thumb":{"w":150,"h":150,"resize":"crop"},"large":{"w":478,"h":547,"resize":"fit"}}}]},"extended_entities":{"media":[{"id":1155792195565293569,"id_str":"1155792195565293569","indices":[66,89],"media_url":"http:\/\/pbs.twimg.com\/media\/EAoy4NLWkAEUiQO.png","media_url_https":"https:\/\/pbs.twimg.com\/media\/EAoy4NLWkAEUiQO.png","url":"https:\/\/t.co\/aQUiSy9BlU","display_url":"pic.twitter.com\/aQUiSy9BlU","expanded_url":"https:\/\/twitter.com\/Katheri85041383\/status\/1155792230772367360\/photo\/1","type":"photo","sizes":{"small":{"w":478,"h":547,"resize":"fit"},"medium":{"w":478,"h":547,"resize":"fit"},"thumb":{"w":150,"h":150,"resize":"crop"},"large":{"w":478,"h":547,"resize":"fit"}}}]},"source":"\u003ca href=\"https:\/\/mobile.twitter.com\" rel=\"nofollow\"\u003eTwitter Web App\u003c\/a\u003e","in_reply_to_status_id":null,"in_reply_to_status_id_str":null,"in_reply_to_user_id":null,"in_reply_to_user_id_str":null,"in_reply_to_screen_name":null,"user":{"id":1153163618461995008,"id_str":"1153163618461995008","name":"KatherineColeman","screen_name":"Katheri85041383","location":"","description":"Evil thinker. Web fanatic. Lifelong internet trailblazer. Travel expert. Problem solver.","url":null,"entities":{"description":{"urls":[]}},"protected":false,"followers_count":0,"friends_count":0,"listed_count":0,"created_at":"Mon Jul 22 04:43:26 +0000 2019","favourites_count":0,"utc_offset":null,"time_zone":null,"geo_enabled":false,"verified":false,"statuses_count":3,"lang":null,"contributors_enabled":false,"is_translator":false,"is_translation_enabled":false,"profile_background_color":"F5F8FA","profile_background_image_url":null,"profile_background_image_url_https":null,"profile_background_tile":false,"profile_image_url":"http:\/\/pbs.twimg.com\/profile_images\/1153163765656854529\/udd2iZX3_normal.jpg","profile_image_url_https":"https:\/\/pbs.twimg.com\/profile_images\/1153163765656854529\/udd2iZX3_normal.jpg","profile_link_color":"1DA1F2","profile_sidebar_border_color":"C0DEED","profile_sidebar_fill_color":"DDEEF6","profile_text_color":"333333","profile_use_background_image":true,"has_extended_profile":false,"default_profile":true,"default_profile_image":false,"following":false,"follow_request_sent":false,"notifications":false,"translator_type":"none"},"geo":null,"coordinates":null,"place":null,"contributors":null,"is_quote_status":false,"retweet_count":0,"favorite_count":0,"favorited":false,"retweeted":false,"possibly_sensitive":false,"possibly_sensitive_appealable":false,"lang":"en"}